odoo/addons/stock_unique_order_per_location/README.rst
odoo/addons/stock_unique_order_per_location/__init__.py
odoo/addons/stock_unique_order_per_location/__manifest__.py
odoo/addons/stock_unique_order_per_location/i18n/it.po
odoo/addons/stock_unique_order_per_location/i18n/stock_unique_order_per_location.pot
odoo/addons/stock_unique_order_per_location/models/__init__.py
odoo/addons/stock_unique_order_per_location/models/stock_move_line.py
odoo/addons/stock_unique_order_per_location/models/stock_picking_type.py
odoo/addons/stock_unique_order_per_location/readme/CONTRIBUTORS.rst
odoo/addons/stock_unique_order_per_location/readme/DESCRIPTION.rst
odoo/addons/stock_unique_order_per_location/static/description/icon.png
odoo/addons/stock_unique_order_per_location/static/description/index.html
odoo/addons/stock_unique_order_per_location/tests/__init__.py
odoo/addons/stock_unique_order_per_location/tests/test_stock_uique_order_per_location.py
odoo/addons/stock_unique_order_per_location/views/stock_picking_type_views.xml
odoo14_addon_stock_unique_order_per_location-14.0.1.0.1.dev8.dist-info/METADATA
odoo14_addon_stock_unique_order_per_location-14.0.1.0.1.dev8.dist-info/WHEEL
odoo14_addon_stock_unique_order_per_location-14.0.1.0.1.dev8.dist-info/top_level.txt
odoo14_addon_stock_unique_order_per_location-14.0.1.0.1.dev8.dist-info/RECORD
